Metadata-Version: 1.0
Name: is-palindrome-PS
Version: 0.0.6
Summary: This is a palindrome checking function.
Home-page: https://balajibetadur.github.io
Author: Prakash Shelar
Author-email: UNKNOWN
License: MIT
Keywords: palindrome,python palindrome,palindrome evaluator
Platform: UNKNOWN
